{
    "os": "macOS-10.16-x86_64-i386-64bit",
    "python": "3.8.12",
    "heartbeatAt": "2021-12-27T06:39:01.051209",
    "startedAt": "2021-12-27T06:38:57.606801",
    "docker": null,
    "cpu_count": 4,
    "cuda": null,
    "args": [
        "--model_export",
        "model_export:latest",
        "--test_data",
        "data_test.csv:latest"
    ],
    "state": "running",
    "program": "run.py",
    "codePath": "evaluate/run.py",
    "git": {
        "remote": "https://github.com/jobquiroz/genre_classification.git",
        "commit": "7d3735a28e471d95d661ab8232487326d52dd567"
    },
    "email": "jobquiroz@hotmail.com",
    "root": "/Users/jobquiroz/OneDrive/MachineLearningChampion/10_UdacityMLOps/genre_classification",
    "host": "Jobs-MacBook-Pro.local",
    "username": "jobquiroz",
    "executable": "/Users/jobquiroz/opt/anaconda3/envs/mlflow-68a4640c065d27be20adcd26ab37011464be4617/bin/python"
}
